low_code_assistant/DominoLogoGrey.svg
low_code_assistant/DominoLogoWhite.svg
low_code_assistant/__init__.py
low_code_assistant/action.py
low_code_assistant/action_ui.py
low_code_assistant/actions_store.py
low_code_assistant/app.py
low_code_assistant/app_entrypoint.py
low_code_assistant/code.py
low_code_assistant/code.vue
low_code_assistant/components.py
low_code_assistant/crossfilter_widgets.py
low_code_assistant/css.py
low_code_assistant/css.vue
low_code_assistant/df_select.py
low_code_assistant/df_select.vue
low_code_assistant/domino_api.py
low_code_assistant/domino_lab_mock.py
low_code_assistant/express.py
low_code_assistant/hooks.py
low_code_assistant/layout.py
low_code_assistant/logging_workaround.py
low_code_assistant/nb_app.py
low_code_assistant/py36.py
low_code_assistant/sample_project_md.py
low_code_assistant/serialize.py
low_code_assistant/settings.py
low_code_assistant/thumbnail.py
low_code_assistant/util.py
low_code_assistant/widgets.py
low_code_assistant/assistant/__init__.py
low_code_assistant/assistant/assistant.py
low_code_assistant/assistant/assistant.vue
low_code_assistant/assistant/drawer.py
low_code_assistant/assistant/drawer.vue
low_code_assistant/assistant/handle_user_install.py
low_code_assistant/assistant/menu.vue
low_code_assistant/assistant/mixpanel.py
low_code_assistant/assistant/mixpanel.vue
low_code_assistant/assistant/notebook.py
low_code_assistant/data/__init__.py
low_code_assistant/data/penguins.csv
low_code_assistant/data/small_molecule_drugbank.csv
low_code_assistant/deploy/__init__.py
low_code_assistant/deploy/app_checker.py
low_code_assistant/deploy/app_checker.vue
low_code_assistant/deploy/button_clipboard.py
low_code_assistant/deploy/button_clipboard.vue
low_code_assistant/deploy/deploy-sync.png
low_code_assistant/deploy/deployer.py
low_code_assistant/deploy/filesystem_watcher.py
low_code_assistant/deploy/filesystem_watcher.vue
low_code_assistant/jupyter/__init__.py
low_code_assistant/jupyter/mixpanel_handler.py
low_code_assistant-1.0.3.dist-info/METADATA
low_code_assistant-1.0.3.dist-info/WHEEL
low_code_assistant-1.0.3.dist-info/licenses/LICENSE.md
low_code_assistant-1.0.3.dist-info/RECORD
