Metadata-Version: 2.1
Name: low-code-assistant
Version: 1.0.3
Project-URL: Home, https://github.com/dominodatalab/low-code-assistant
Author-email: "Maarten A. Breddels" <maartenbreddels@gmail.com>, Mario Buikhuizen <mariobuikhuizen@gmail.com>
License-File: LICENSE.md
Requires-Dist: dominodatalab; python_version >= '3.8'
Requires-Dist: humanize
Requires-Dist: ipyvue
Requires-Dist: ipyvuetify
Requires-Dist: ipywidgets<8
Requires-Dist: nbformat>=4.5
Requires-Dist: notebook>=4.6
Requires-Dist: openpyxl
Requires-Dist: pandas
Requires-Dist: plotly>=5.5
Requires-Dist: pydantic
Requires-Dist: reacton~=1.0.0
Requires-Dist: solara[assets]~=1.1.1
Requires-Dist: xlrd
Provides-Extra: dev
Requires-Dist: black; extra == 'dev'
Requires-Dist: bump2version; extra == 'dev'
Requires-Dist: dominodatalab-data; extra == 'dev'
Requires-Dist: flake8; extra == 'dev'
Requires-Dist: playwright==1.19.0; extra == 'dev'
Requires-Dist: pre-commit; extra == 'dev'
Requires-Dist: pytest; extra == 'dev'
Requires-Dist: pytest-cov; extra == 'dev'
Requires-Dist: pytest-mock; extra == 'dev'
Requires-Dist: pytest-playwright; extra == 'dev'
Requires-Dist: pytest-timeout; extra == 'dev'
Requires-Dist: python-dotenv; extra == 'dev'
Requires-Dist: redshift-connector; extra == 'dev'
Requires-Dist: snowflake-connector-python; extra == 'dev'
Requires-Dist: types-requests; extra == 'dev'
